MANIFEST.in
README.md
conf.py
setup.py
version.py
capiq_excel/__init__.py
capiq_excel/addin.py
capiq_excel/combine.py
capiq_excel/exceptions.py
capiq_excel/fileops.py
capiq_excel/ids.py
capiq_excel/main.py
capiq_excel.egg-info/PKG-INFO
capiq_excel.egg-info/SOURCES.txt
capiq_excel.egg-info/dependency_links.txt
capiq_excel.egg-info/requires.txt
capiq_excel.egg-info/top_level.txt
capiq_excel/downloader/__init__.py
capiq_excel/downloader/timeout.py
capiq_excel/downloader/tools.py
capiq_excel/tools/__init__.py
capiq_excel/tools/dates.py
capiq_excel/tools/ext_pandas.py
capiq_excel/workbook/__init__.py
capiq_excel/workbook/commands.py
capiq_excel/workbook/create.py
capiq_excel/workbook/wait.py
capiq_excel/workbook/populate/__init__.py
capiq_excel/workbook/populate/extract.py
capiq_excel/workbook/populate/main.py
capiq_excel/workbook/populate/replace.py
test/__init__.py
test/conftest.py
test/test_download.py