Metadata-Version: 1.2
Name: capiq-excel
Version: 0.4.2
Summary: Capital IQ Data Downloader using Python to drive Excel Plugin
Home-page: https://github.com/nickderobertis/capiq-excel-downloader-py/
Author: Nick DeRobertis
Author-email: whoopnip@gmail.com
License: MIT
Project-URL: Code, https://github.com/nickderobertis/capiq-excel-downloader-py/
Project-URL: Documentation, https://nickderobertis.github.io/capiq-excel-downloader-py/
Platform: UNKNOWN
Classifier: Development Status :: 3 - Alpha
Classifier: Intended Audience :: Developers
Classifier: Programming Language :: Python :: 3.6
Classifier: Programming Language :: Python :: 3.7
